IDA/IDA_main.py
IDA/Image_reader.py
IDA/JFIFDecoder.py
IDA/__init__.py
image_decoding_algorithms-0.0.2.dist-info/METADATA
image_decoding_algorithms-0.0.2.dist-info/WHEEL
image_decoding_algorithms-0.0.2.dist-info/top_level.txt
image_decoding_algorithms-0.0.2.dist-info/RECORD
