Metadata-Version: 2.1
Name: image-decoding-algorithms
Version: 0.0.2
Summary: Scripts for decoding an image
Home-page: https://github.com/gejirz/image-decoding-algorithms
Author: Victor Andrievskiy
Author-email: superavb222@gmail.com
License: MIT License
Keywords: python,image decoding,JFIF,jpeg,decoding,baseline encoding
Platform: UNKNOWN
Requires-Dist: scikit-image
Requires-Dist: numpy
